datapact/__init__.py
datapact/datapact.py
datapact/javascript/__init__.py
datapact/javascript/entrypoint.js
datapact/util/__init__.py
datapact/util/github.py
datapact/util/session_fingerprint.py
datapact-0.9.0.dist-info/LICENSE
datapact-0.9.0.dist-info/METADATA
datapact-0.9.0.dist-info/WHEEL
datapact-0.9.0.dist-info/top_level.txt
datapact-0.9.0.dist-info/RECORD
